{
  "version": "metrics_v1",
  "run_id": "onnxlab_20260621T131542Z_minimal_onnx_mt5_plumbing",
  "metric_scope": "fixed_fixture_plumbing_only",
  "dataset_rows": 6205,
  "feature_label_rows": 6203,
  "train_candidate_rows": 4342,
  "train_fit_rows": 4341,
  "purged_rows": 1,
  "validation_rows": 1861,
  "split_boundary_status": "passed_label_end_time_lt_first_validation_time",
  "python_onnxruntime_abs_error": 2.703020651750876e-08,
  "python_onnxruntime_tolerance": 1e-05,
  "mt5_native_onnx_abs_error": 0.0,
  "claim_boundary": "fixed_fixture_parity_learning_only_not_performance_metrics",
  "mt5_native_onnx_tolerance": 1e-05,
  "mt5_native_onnx_status": "matched",
  "mt5_native_onnx_output_path": "runtime/mt5_attempts/attempt_20260621T131542Z_mt5_onnx_fixture_v0/telemetry/mt5_probe_output.csv",
  "result_judgment": "preserved_clue"
}
